address_parser_js-0.1.1.dist-info/METADATA
address_parser_js-0.1.1.dist-info/WHEEL
address_parser_js-0.1.1.dist-info/entry_points.txt
parse/__init__.py
parse/area.py
parse/index.js
parse/parse_address.py
parse/parse_area.py
parse/utils.py
address_parser_js-0.1.1.dist-info/RECORD
