Metadata-Version: 2.1
Name: address_parser_js
Version: 0.1.1
Summary: 中文地址解析
Author-Email: dinger <dinger2dinger@gmail.com>
License: MIT
Project-URL: Homepage, https://github.com/dingtwo/address_parser
Project-URL: Issues, https://github.com/dingtwo/address_parser/issues
Requires-Python: ==3.13.*
